[{"url": "/goodreads/the-uninhabitable-earth/index.html", "title": "The Uninhabitable Earth", "date": 1576540800000, "score": 2.82972173889478, "detailed_score": [1.0, 0.3333333333333333, 0.9975922703742981]}, {"url": "/goodreads/the-immortal-life-of-henrietta-lacks/index.html", "title": "The Immortal Life of Henrietta Lacks", "date": 1439856000000, "score": 2.737529695034027, "detailed_score": [1.0, 0.25, 0.9916864633560181]}, {"url": "/goodreads/in-extremis-the-life-of-war-correspondent-marie-colvin/index.html", "title": "In Extremis: The Life of War Correspondent Marie Colvin", "date": 1600646400000, "score": 2.6747979640960695, "detailed_score": [1.0, 0.2, 0.9831986427307129]}, {"url": "/goodreads/i-contain-multitudes-the-microbes-within-us-and-a-grander-view-of-life/index.html", "title": "I Contain Multitudes: The Microbes Within Us and a Grander View of Life", "date": 1510358400000, "score": 2.6632011632124586, "detailed_score": [1.0, 0.16666666666666666, 0.9976896643638611]}, {"url": "/goodreads/shady-characters-the-secret-life-of-punctuation-symbols-other-typographical-marks/index.html", "title": "Shady Characters: The Secret Life of Punctuation, Symbols & Other Typographical Marks", "date": 1390724137000, "score": 2.6532242389825673, "detailed_score": [1.0, 0.15384615384615385, 0.9995853900909424]}, {"url": "/goodreads/travels-with-epicurus-meditations-from-a-greek-island-on-the-pleasures-of-old-age/index.html", "title": "Travels With Epicurus: Meditations from a Greek Island on the Pleasures of Old Age", "date": 1455148800000, "score": 2.499895304441452, "detailed_score": [1.0, 0.0, 0.999930202960968]}, {"url": "/goodreads/the-volunteer-the-true-story-of-the-resistance-hero-who-infiltrated-auschwitz/index.html", "title": "The Volunteer: The True Story of the Resistance Hero who Infiltrated Auschwitz", "date": 1598745600000, "score": 2.4993510842323303, "detailed_score": [1.0, 0.0, 0.9995673894882202]}, {"url": "/goodreads/in-the-heart-of-the-sea-the-tragedy-of-the-whaleship-essex/index.html", "title": "In the Heart of the Sea: The Tragedy of the Whaleship Essex", "date": 1472947200000, "score": 2.49913489818573, "detailed_score": [1.0, 0.0, 0.9994232654571533]}, {"url": "/goodreads/the-weather-machine-how-we-see-into-the-future/index.html", "title": "The Weather Machine: How We See Into the Future", "date": 1570861093000, "score": 2.4991137981414795, "detailed_score": [1.0, 0.0, 0.9994091987609863]}, {"url": "/goodreads/travels-with-herodotus/index.html", "title": "Travels with Herodotus", "date": 1590451200000, "score": 2.4989306926727295, "detailed_score": [1.0, 0.0, 0.9992871284484863]}]