[{"url": "/goodreads/empire-how-britain-made-the-modern-world/index.html", "title": "Empire: How Britain Made the Modern World", "date": 1352598225000, "score": 2.79630682034926, "detailed_score": [0.8, 0.5454545454545454, 0.9672348499298096]}, {"url": "/goodreads/stoned-jewelry-obsession-and-how-desire-shapes-the-world/index.html", "title": "Stoned: Jewelry, Obsession, and How Desire Shapes the World", "date": 1637452800000, "score": 2.6640497247378034, "detailed_score": [1.0, 0.16666666666666666, 0.9982553720474243]}, {"url": "/goodreads/the-curse-of-bigness-how-corporate-giants-came-to-rule-the-world/index.html", "title": "The Curse of Bigness: How Corporate Giants Came to Rule the World", "date": 1680331427000, "score": 2.6505018862394185, "detailed_score": [1.0, 0.15384615384615385, 0.9977704882621765]}, {"url": "/goodreads/exactly-how-precision-engineers-created-the-modern-world/index.html", "title": "Exactly: How Precision Engineers Created the Modern World", "date": 1585440000000, "score": 2.6331810732682546, "detailed_score": [0.8, 0.3333333333333333, 0.9998984932899475]}, {"url": "/goodreads/between-the-world-and-me/index.html", "title": "Between the World and Me", "date": 1466035200000, "score": 2.584932511193412, "detailed_score": [0.8, 0.2857142857142857, 0.999478816986084]}, {"url": "/goodreads/the-world-until-yesterday/index.html", "title": "The World Until Yesterday", "date": 1489622400000, "score": 2.5498643696308134, "detailed_score": [0.8, 0.25, 0.9999095797538757]}, {"url": "/goodreads/the-covent-garden-ladies/index.html", "title": "The Covent Garden Ladies", "date": 1642809600000, "score": 2.4999991953372955, "detailed_score": [1.0, 0.0, 0.999999463558197]}, {"url": "/goodreads/american-kingpin-the-epic-hunt-for-the-criminal-mastermind-behind-the-silk-road/index.html", "title": "American Kingpin: The Epic Hunt for the Criminal Mastermind Behind the Silk Road", "date": 1613606400000, "score": 2.499945729970932, "detailed_score": [1.0, 0.0, 0.9999638199806213]}, {"url": "/goodreads/herding-hemingways-cats-understanding-how-our-genes-work/index.html", "title": "Herding Hemingway's Cats: Understanding how our genes work", "date": 1669527082000, "score": 2.4997598528862, "detailed_score": [1.0, 0.0, 0.9998399019241333]}, {"url": "/goodreads/herding-hemingways-cats-understanding-how-our-genes-work-bloomsbury-sigma/index.html", "title": "Herding Hemingway's Cats: Understanding how our genes work (Bloomsbury Sigma)", "date": 1669527082000, "score": 2.499759763479233, "detailed_score": [1.0, 0.0, 0.9998398423194885]}]