[{"url": "/goodreads/invasive-aliens-the-plants-and-animals-from-over-there-that-are-over-here/index.html", "title": "Invasive Aliens: The Plants and Animals from Over There That Are Over Here", "date": 1630454400000, "score": 2.5, "detailed_score": [1.0, 0.0, 1.0]}, {"url": "/goodreads/pure-invention-how-japan-made-the-modern-world/index.html", "title": "Pure Invention: How Japan Made the Modern World", "date": 1650844800000, "score": 2.499993920326233, "detailed_score": [1.0, 0.0, 0.9999959468841553]}, {"url": "/goodreads/diary-of-an-mps-wife-inside-and-outside-power/index.html", "title": "Diary of an MP's Wife: Inside and Outside Power", "date": 1708646400000, "score": 2.4999805986881256, "detailed_score": [1.0, 0.0, 0.9999870657920837]}, {"url": "/goodreads/the-storm-is-upon-us-how-qanon-became-a-movement-cult-and-conspiracy-theory-of-everything/index.html", "title": "The Storm Is Upon Us: How QAnon Became a Movement, Cult, and Conspiracy Theory of Everything", "date": 1670803200000, "score": 2.4998878836631775, "detailed_score": [1.0, 0.0, 0.9999252557754517]}, {"url": "/goodreads/fracture-stories-of-how-great-lives-take-root-in-trauma/index.html", "title": "Fracture: Stories of How Great Lives Take Root in Trauma", "date": 1631577600000, "score": 2.4998729526996613, "detailed_score": [1.0, 0.0, 0.9999153017997742]}, {"url": "/goodreads/the-secret-history-of-wonder-woman/index.html", "title": "The Secret History of Wonder Woman", "date": 1658534400000, "score": 2.499787747859955, "detailed_score": [1.0, 0.0, 0.9998584985733032]}, {"url": "/goodreads/the-ruin-of-all-witches-life-and-death-in-the-new-world/index.html", "title": "The Ruin of All Witches: Life and Death in the New World", "date": 1682553600000, "score": 2.499716490507126, "detailed_score": [1.0, 0.0, 0.9998109936714172]}, {"url": "/goodreads/estates-an-intimate-history/index.html", "title": "Estates: An Intimate History", "date": 1702944000000, "score": 2.499500036239624, "detailed_score": [1.0, 0.0, 0.999666690826416]}, {"url": "/goodreads/how-to-live-a-life-of-montaigne-in-one-question-and-twenty-attempts-at-an-answer/index.html", "title": "How to Live: A Life of Montaigne in One Question and Twenty Attempts at an Answer", "date": 1498694400000, "score": 2.499436378479004, "detailed_score": [1.0, 0.0, 0.9996242523193359]}, {"url": "/goodreads/between-two-fires-truth-ambition-and-compromise-in-putins-russia/index.html", "title": "Between Two Fires: Truth, Ambition, and Compromise in Putin's Russia", "date": 1690588800000, "score": 2.4994116127490997, "detailed_score": [1.0, 0.0, 0.9996077418327332]}]