[{"url": "/goodreads/travellers-in-the-third-reich/index.html", "title": "Travellers in the Third Reich", "date": 1635206400000, "score": 2.5, "detailed_score": [1.0, 0.0, 1.0]}, {"url": "/goodreads/the-darien-disaster-a-scots-colony-in-the-new-world-1698-1700/index.html", "title": "The Darien Disaster: a Scots Colony in the New World, 1698 - 1700", "date": 1665810290000, "score": 2.4999998211860657, "detailed_score": [1.0, 0.0, 0.9999998807907104]}, {"url": "/goodreads/station-eleven/index.html", "title": "Station Eleven", "date": 1496102400000, "score": 2.4999982118606567, "detailed_score": [1.0, 0.0, 0.9999988079071045]}, {"url": "/goodreads/riddle-and-the-knight/index.html", "title": "Riddle And The Knight", "date": 1566299147000, "score": 2.49999463558197, "detailed_score": [1.0, 0.0, 0.9999964237213135]}, {"url": "/goodreads/the-house-that-hitler-built/index.html", "title": "The House That Hitler Built", "date": 1596844800000, "score": 2.4999839067459106, "detailed_score": [1.0, 0.0, 0.9999892711639404]}, {"url": "/goodreads/dopesick-dealers-doctors-and-the-drug-company-that-addicted-america/index.html", "title": "Dopesick: Dealers, Doctors, and the Drug Company that Addicted America", "date": 1640217600000, "score": 2.4999713003635406, "detailed_score": [1.0, 0.0, 0.9999808669090271]}, {"url": "/goodreads/the-rivals-of-sherlock-holmes-early-detective-stories/index.html", "title": "The Rivals Of Sherlock Holmes: Early Detective Stories", "date": 1482985382000, "score": 2.499956727027893, "detailed_score": [1.0, 0.0, 0.9999711513519287]}, {"url": "/goodreads/infinite-detail/index.html", "title": "Infinite Detail", "date": 1610179341000, "score": 2.499932587146759, "detailed_score": [1.0, 0.0, 0.9999550580978394]}, {"url": "/goodreads/his-bloody-project-documents-relating-to-the-case-of-roderick-macrae/index.html", "title": "His Bloody Project: Documents Relating to the Case of Roderick Macrae", "date": 1543741040000, "score": 2.49993097782135, "detailed_score": [1.0, 0.0, 0.9999539852142334]}, {"url": "/goodreads/accidental-gods-on-men-unwittingly-turned-divine/index.html", "title": "Accidental Gods: On Men Unwittingly Turned Divine", "date": 1665811839000, "score": 2.499913990497589, "detailed_score": [1.0, 0.0, 0.9999426603317261]}]