[{"url": "/goodreads/no-one-would-listen/index.html", "title": "No One Would Listen", "date": 1365239651000, "score": 2.5, "detailed_score": [1.0, 0.0, 1.0]}, {"url": "/goodreads/a-distant-mirror-the-calamitous-14th-century/index.html", "title": "A Distant Mirror: The Calamitous 14th Century", "date": 1360646106000, "score": 2.5, "detailed_score": [1.0, 0.0, 1.0]}, {"url": "/goodreads/the-guns-of-august/index.html", "title": "The Guns of August", "date": 1360646106000, "score": 2.5, "detailed_score": [1.0, 0.0, 1.0]}, {"url": "/goodreads/the-sandman-vol-9-the-kindly-ones/index.html", "title": "The Sandman, Vol. 9: The Kindly Ones", "date": 1333112721000, "score": 2.5, "detailed_score": [1.0, 0.0, 1.0]}, {"url": "/goodreads/the-sandman-vol-1-preludes-nocturnes/index.html", "title": "The Sandman, Vol. 1: Preludes & Nocturnes", "date": 1333112678000, "score": 2.5, "detailed_score": [1.0, 0.0, 1.0]}, {"url": "/goodreads/the-artist-the-philosopher-and-the-warrior-the-intersecting-lives-of-da-vinci-machiavelli-and-borgia-and-the-world-they-shaped/index.html", "title": "The Artist, the Philosopher, and the Warrior: The Intersecting Lives of Da Vinci, Machiavelli, and Borgia and the World They Shaped", "date": 1333112425000, "score": 2.5, "detailed_score": [1.0, 0.0, 1.0]}, {"url": "/goodreads/neuromancer-sprawl-1/index.html", "title": "Neuromancer (Sprawl, #1)", "date": 1333112295000, "score": 2.5, "detailed_score": [1.0, 0.0, 1.0]}, {"url": "/goodreads/animal-farm-1984/index.html", "title": "Animal Farm / 1984", "date": 1333112292000, "score": 2.5, "detailed_score": [1.0, 0.0, 1.0]}, {"url": "/goodreads/hyperion-hyperion-cantos-1/index.html", "title": "Hyperion (Hyperion Cantos, #1)", "date": 1333112046000, "score": 2.5, "detailed_score": [1.0, 0.0, 1.0]}, {"url": "/goodreads/accelerando-singularity/index.html", "title": "Accelerando (Singularity)", "date": 1333111992000, "score": 2.5, "detailed_score": [1.0, 0.0, 1.0]}]