[{"url": "/2013/07/26/improvements/index.html", "title": "Some improvements to SleepySketch", "date": 1374852038000, "score": 2.495318297545115, "detailed_score": [0.6666666666666666, 0.4, 0.9524344205856323]}, {"url": "/2013/06/28/soldering/index.html", "title": "First bit of soldering done", "date": 1372437897000, "score": 2.1895405522414615, "detailed_score": [0.5, 0.2857142857142857, 0.9358841776847839]}, {"url": "/2013/07/25/sleepy-sketches/index.html", "title": "Sleepy sketches", "date": 1374753601000, "score": 2.1594422260920205, "detailed_score": [0.6666666666666666, 0.0, 0.9951837062835693]}, {"url": "/2013/08/27/arduino-breadboard/index.html", "title": "Low-power Arduino-on-a-breadboard", "date": 1377600465000, "score": 2.1249005595842996, "detailed_score": [0.6666666666666666, 0.0, 0.9721559286117554]}, {"url": "/2013/07/23/arduino-watchdog/index.html", "title": "Understanding Arduino sleep modes: the watchdog timer", "date": 1374589287000, "score": 2.09370539188385, "detailed_score": [0.6, 0.0, 0.9958035945892334]}, {"url": "/2013/07/31/power/index.html", "title": "Basic power measurements", "date": 1375290775000, "score": 2.067948228120804, "detailed_score": [0.6, 0.0, 0.9786321520805359]}, {"url": "/2013/07/03/xbee-arduino/index.html", "title": "The xbee-arduino library", "date": 1372836622000, "score": 2.04073623418808, "detailed_score": [0.6, 0.0, 0.9604908227920532]}, {"url": "/2013/10/08/s4a/index.html", "title": "Scratch: visual programming for Arduino", "date": 1381215612000, "score": 1.9661877155303955, "detailed_score": [0.5, 0.0, 0.9774584770202637]}, {"url": "/2013/07/02/xctu/index.html", "title": "XBee firmware management with X-CTU", "date": 1372752034000, "score": 1.9599910951577701, "detailed_score": [0.46153846153846156, 0.0, 0.9989684224128723]}, {"url": "/2013/08/02/xbee-sleeping/index.html", "title": "XBee sleeping", "date": 1375454490000, "score": 1.9598096446557478, "detailed_score": [0.5454545454545454, 0.0, 0.9429033994674683]}]