[{"url": "/2010/12/16/inauguration/index.html", "title": "Inauguration", "date": 1292486404000, "score": 2.166390667359034, "detailed_score": [0.6666666666666666, 0.0, 0.9998160004615784]}, {"url": "/2011/07/01/metrics/index.html", "title": "Metrics and the Research Evaluation Framework", "date": 1309503629000, "score": 2.1663476626078286, "detailed_score": [0.6666666666666666, 0.0, 0.9997873306274414]}, {"url": "/2011/07/05/arts-humanities/index.html", "title": "On not funding the arts and humanities", "date": 1309849213000, "score": 2.1656865874926248, "detailed_score": [0.6666666666666666, 0.0, 0.9993466138839722]}, {"url": "/2012/07/11/call-papers-midsens-2012/index.html", "title": "Call for papers: Midsens 2012", "date": 1342008026000, "score": 1.9999844431877136, "detailed_score": [0.5, 0.0, 0.9999896287918091]}, {"url": "/2010/10/29/academic-stereotypes/index.html", "title": "The three academic stereotypes", "date": 1288335609000, "score": 1.9999294579029083, "detailed_score": [0.5, 0.0, 0.9999529719352722]}, {"url": "/2011/11/07/phd-leuven/index.html", "title": "Studentships in wireless sensor networks in Leuven", "date": 1320665942000, "score": 1.9999138116836548, "detailed_score": [0.5, 0.0, 0.9999425411224365]}, {"url": "/2011/02/25/hiring-2/index.html", "title": "Hiring academics", "date": 1298620835000, "score": 1.9998496174812317, "detailed_score": [0.5, 0.0, 0.9998997449874878]}, {"url": "/2010/05/08/grey-philistines/index.html", "title": "Are the grey philistines really in charge?", "date": 1273339739000, "score": 1.9997763931751251, "detailed_score": [0.5, 0.0, 0.9998509287834167]}, {"url": "/2010/10/22/first-year/index.html", "title": "The first year", "date": 1287735317000, "score": 1.999719887971878, "detailed_score": [0.5, 0.0, 0.9998132586479187]}, {"url": "/2011/09/08/people-university/index.html", "title": "Why do people go to university?", "date": 1315479409000, "score": 1.9995792508125305, "detailed_score": [0.5, 0.0, 0.999719500541687]}]