[{"url": "/2015/03/10/studentships-st-andrews/index.html", "title": "PhD studentships in St Andrews", "date": 1425988040000, "score": 2.9312048819330006, "detailed_score": [1.0, 0.4444444444444444, 0.9911736249923706]}, {"url": "/2013/12/09/funded-phd-positions/index.html", "title": "Funded PhD positions available", "date": 1386582361000, "score": 2.722141398323907, "detailed_score": [1.0, 0.2222222222222222, 0.999946117401123]}, {"url": "/2015/02/03/phd-cs-med/index.html", "title": "Fully-funded PhD scholarship available", "date": 1422965538000, "score": 2.385098569922977, "detailed_score": [0.6666666666666666, 0.2222222222222222, 0.9974731206893921]}, {"url": "/2015/09/18/phd-data-science/index.html", "title": "PhD data science studentships available at Trinity College Dublin", "date": 1442573657000, "score": 2.337865016552118, "detailed_score": [0.4, 0.46153846153846156, 0.9842177033424377]}, {"url": "/2012/02/22/studentships/index.html", "title": "Studentships available", "date": 1329926215000, "score": 2.279172109706061, "detailed_score": [0.5, 0.2857142857142857, 0.9956385493278503]}, {"url": "/2012/04/26/brazil-science/index.html", "title": "Brazilian \"Science without Borders\" studentships available", "date": 1335444378000, "score": 2.1739215796644036, "detailed_score": [0.5, 0.18181818181818182, 0.994735598564148]}, {"url": "/2012/12/20/600th-scholarships/index.html", "title": "Six 600th anniversary PhD scholarships", "date": 1356031342000, "score": 2.169989746809006, "detailed_score": [0.5, 0.2, 0.9799931645393372]}, {"url": "/2012/05/17/5-studentships/index.html", "title": "5 studentships in Computer Science and St Andrews", "date": 1337251377000, "score": 2.164139921014959, "detailed_score": [0.5, 0.18181818181818182, 0.9882144927978516]}, {"url": "/2012/08/03/mscphd-wireless-location/index.html", "title": "MSc/PhD positions available in wireless location systems", "date": 1343991379000, "score": 2.148593763510386, "detailed_score": [0.6666666666666666, 0.0, 0.987951397895813]}, {"url": "/2011/06/06/phd/index.html", "title": "PhD position available in intrusion detection", "date": 1307352776000, "score": 2.0989338219165803, "detailed_score": [0.4, 0.2, 0.9992892146110535]}]