[{"url": "/goodreads/estates-an-intimate-history/index.html", "title": "Estates: An Intimate History", "date": 1702944000000, "score": 2.7422220408916473, "detailed_score": [1.0, 0.25, 0.9948146939277649]}, {"url": "/goodreads/seven-games-a-human-history/index.html", "title": "Seven Games: A Human History", "date": 1651449600000, "score": 2.735447778966692, "detailed_score": [0.8, 0.4444444444444444, 0.9940022230148315]}, {"url": "/goodreads/the-secret-history-of-wonder-woman/index.html", "title": "The Secret History of Wonder Woman", "date": 1658534400000, "score": 2.715755773915185, "detailed_score": [1.0, 0.2222222222222222, 0.9956890344619751]}, {"url": "/goodreads/the-matter-of-the-heart-a-history-of-the-heart-in-eleven-operations/index.html", "title": "The Matter of the Heart: A History of the Heart in Eleven Operations", "date": 1682640000000, "score": 2.6635008400136773, "detailed_score": [1.0, 0.18181818181818182, 0.9877884387969971]}, {"url": "/goodreads/unix-a-history-and-a-memoir/index.html", "title": "UNIX: A History and a Memoir", "date": 1672617600000, "score": 2.5499467134475706, "detailed_score": [0.8, 0.25, 0.9999644756317139]}, {"url": "/goodreads/the-shortest-history-of-germany/index.html", "title": "The Shortest History of Germany", "date": 1554854400000, "score": 2.54844816327095, "detailed_score": [0.8, 0.25, 0.9989654421806335]}, {"url": "/goodreads/sapiens-a-brief-history-of-humankind/index.html", "title": "Sapiens: A Brief History of Humankind", "date": 1503187200000, "score": 2.5217092944516075, "detailed_score": [0.8, 0.2222222222222222, 0.9996580481529236]}, {"url": "/goodreads/homo-deus-a-history-of-tomorrow/index.html", "title": "Homo Deus: A History of Tomorrow", "date": 1519430400000, "score": 2.520957292450799, "detailed_score": [0.8, 0.2222222222222222, 0.9991567134857178]}, {"url": "/goodreads/testosterone-the-story-of-the-hormone-that-dominates-and-divides-us/index.html", "title": "Testosterone: The Story of the Hormone that Dominates and Divides Us", "date": 1648425600000, "score": 2.4999996423721313, "detailed_score": [1.0, 0.0, 0.9999997615814209]}, {"url": "/goodreads/the-power-of-geography-ten-maps-that-reveal-the-future-of-our-world/index.html", "title": "The Power of Geography: Ten Maps That Reveal the Future of Our World", "date": 1697760000000, "score": 2.4999628961086273, "detailed_score": [1.0, 0.0, 0.9999752640724182]}]