[{"url": "/goodreads/poverty-safari/index.html", "title": "Poverty Safari", "date": 1542437942000, "score": 2.497538983821869, "detailed_score": [1.0, 0.0, 0.9983593225479126]}, {"url": "/goodreads/who-got-einsteins-office-eccentricity-and-genius-at-the-institute-for-advanced-study/index.html", "title": "Who Got Einstein's Office? Eccentricity and Genius at the Institute for Advanced Study", "date": 1376295438000, "score": 2.4844489097595215, "detailed_score": [1.0, 0.0, 0.9896326065063477]}, {"url": "/goodreads/ghost-in-the-wires-my-adventures-as-the-worlds-most-wanted-hacker/index.html", "title": "Ghost in the Wires: My Adventures as the World's Most Wanted Hacker", "date": 1367032836000, "score": 2.4584506154060364, "detailed_score": [1.0, 0.0, 0.9723004102706909]}, {"url": "/goodreads/adapt-why-success-always-starts-with-failure/index.html", "title": "Adapt: Why Success Always Starts with Failure", "date": 1363605286000, "score": 2.4521586894989014, "detailed_score": [1.0, 0.0, 0.9681057929992676]}, {"url": "/goodreads/the-twelve-caesars/index.html", "title": "The Twelve Caesars", "date": 1367033129000, "score": 2.4408928751945496, "detailed_score": [1.0, 0.0, 0.9605952501296997]}, {"url": "/goodreads/american-notes-for-general-circulation/index.html", "title": "American Notes For General Circulation", "date": 1424131200000, "score": 2.4272258579730988, "detailed_score": [1.0, 0.0, 0.9514839053153992]}, {"url": "/goodreads/musicophilia-tales-of-music-and-the-brain/index.html", "title": "Musicophilia: Tales of Music and the Brain", "date": 1538718135000, "score": 2.406761586666107, "detailed_score": [1.0, 0.0, 0.9378410577774048]}, {"url": "/goodreads/debt-the-first-5000-years/index.html", "title": "Debt: The First 5,000 Years", "date": 1542437660000, "score": 2.4056368470191956, "detailed_score": [1.0, 0.0, 0.9370912313461304]}, {"url": "/goodreads/an-astronauts-guide-to-life-on-earth/index.html", "title": "An Astronaut's Guide to Life on Earth", "date": 1401014528000, "score": 2.3844153881073, "detailed_score": [1.0, 0.0, 0.9229435920715332]}, {"url": "/goodreads/do-no-harm-stories-of-life-death-and-brain-surgery/index.html", "title": "Do No Harm: Stories of Life, Death and Brain Surgery", "date": 1469232000000, "score": 2.367263376712799, "detailed_score": [1.0, 0.0, 0.9115089178085327]}]