[{"url": "/goodreads/six-days-how-the-1967-war-shaped-the-middle-east/index.html", "title": "Six Days: How the 1967 War Shaped the Middle East", "date": 1404345600000, "score": 2.9615114606343784, "detailed_score": [1.0, 0.46153846153846156, 0.9999819993972778]}, {"url": "/goodreads/verdun-the-longest-battle-of-the-great-war/index.html", "title": "Verdun: The Longest Battle of the Great War", "date": 1519454484000, "score": 2.8621895800937307, "detailed_score": [1.0, 0.36363636363636365, 0.9990354776382446]}, {"url": "/goodreads/why-britain-is-at-war/index.html", "title": "Why Britain is at War", "date": 1380962544000, "score": 2.7490080296993256, "detailed_score": [1.0, 0.25, 0.999338686466217]}, {"url": "/goodreads/great-degeneration/index.html", "title": "Great Degeneration", "date": 1418784481000, "score": 2.7474772930145264, "detailed_score": [1.0, 0.25, 0.9983181953430176]}, {"url": "/goodreads/stalins-war/index.html", "title": "Stalin's War", "date": 1624838400000, "score": 2.746491938829422, "detailed_score": [1.0, 0.25, 0.997661292552948]}, {"url": "/goodreads/a-brief-history-of-the-great-moghuls/index.html", "title": "A Brief History of the Great Moghuls", "date": 1429315200000, "score": 2.697765272855759, "detailed_score": [1.0, 0.2, 0.9985101819038391]}, {"url": "/goodreads/korean-war/index.html", "title": "Korean War", "date": 1375660800000, "score": 2.690740168094635, "detailed_score": [1.0, 0.25, 0.9604934453964233]}, {"url": "/goodreads/the-war-of-the-world/index.html", "title": "The War of the World", "date": 1377043200000, "score": 2.6890102326869965, "detailed_score": [1.0, 0.25, 0.9593401551246643]}, {"url": "/goodreads/strange-landscape-a-journey-through-the-middle-ages/index.html", "title": "Strange landscape: A journey through the Middle Ages", "date": 1383264000000, "score": 2.681598508899862, "detailed_score": [1.0, 0.18181818181818182, 0.9998535513877869]}, {"url": "/goodreads/deadliest-enemy-our-war-against-killer-germs/index.html", "title": "Deadliest Enemy: Our War Against Killer Germs", "date": 1625097600000, "score": 2.680162811821157, "detailed_score": [1.0, 0.18181818181818182, 0.9988964200019836]}]