[{"url": "/2015/03/10/studentships-st-andrews/index.html", "title": "PhD studentships in St Andrews", "date": 1425988040000, "score": 2.7289485931396484, "detailed_score": [1.0, 0.25, 0.9859657287597656]}, {"url": "/2015/03/05/phd-studentships-university-college-cork/index.html", "title": "PhD Studentships at University College Cork", "date": 1425552680000, "score": 2.7214964164627924, "detailed_score": [1.0, 0.2222222222222222, 0.9995161294937134]}, {"url": "/2015/02/03/phd-cs-med/index.html", "title": "Fully-funded PhD scholarship available", "date": 1422965538000, "score": 2.6656728188196817, "detailed_score": [0.6666666666666666, 0.5, 0.9993374347686768]}, {"url": "/2012/08/03/mscphd-wireless-location/index.html", "title": "MSc/PhD positions available in wireless location systems", "date": 1343991379000, "score": 2.5396942834059395, "detailed_score": [0.6666666666666666, 0.4, 0.9820184111595154]}, {"url": "/2011/06/06/phd/index.html", "title": "PhD position available in intrusion detection", "date": 1307352776000, "score": 2.34443764951494, "detailed_score": [0.4, 0.4444444444444444, 0.9999954700469971]}, {"url": "/2012/02/22/studentships/index.html", "title": "Studentships available", "date": 1329926215000, "score": 2.321051587661107, "detailed_score": [0.5, 0.3333333333333333, 0.9918121695518494]}, {"url": "/2017/05/10/proximal-sensing-ucd/index.html", "title": "PhD position in proximal sensing available at UCD Dublin", "date": 1494403285000, "score": 2.2586941253055226, "detailed_score": [0.4, 0.36363636363636365, 0.996705174446106]}, {"url": "/2013/03/07/studentship/index.html", "title": "Studentship available in Newcastle upon Tyne", "date": 1362674963000, "score": 2.2215117944611444, "detailed_score": [0.5, 0.2222222222222222, 0.9995263814926147]}, {"url": "/2015/09/18/phd-data-science/index.html", "title": "PhD data science studentships available at Trinity College Dublin", "date": 1442573657000, "score": 2.217992796500524, "detailed_score": [0.4, 0.3333333333333333, 0.9897729754447937]}, {"url": "/2012/12/20/600th-scholarships/index.html", "title": "Six 600th anniversary PhD scholarships", "date": 1356031342000, "score": 2.2016750706566706, "detailed_score": [0.5, 0.2222222222222222, 0.9863018989562988]}]