[{"url": "/goodreads/a-game-of-you-the-sandman-5/index.html", "title": "A Game of You (The Sandman, #5)", "date": 1333112735000, "score": 2.9442967441346912, "detailed_score": [1.0, 0.4444444444444444, 0.999901533126831]}, {"url": "/goodreads/the-wake-the-sandman-10/index.html", "title": "The Wake (The Sandman, #10)", "date": 1333112731000, "score": 2.9422198202874927, "detailed_score": [1.0, 0.4444444444444444, 0.9985169172286987]}, {"url": "/goodreads/the-dolls-house-the-sandman-2/index.html", "title": "The Doll's House (The Sandman, #2)", "date": 1333112683000, "score": 2.899073475599289, "detailed_score": [1.0, 0.4, 0.9993823170661926]}, {"url": "/goodreads/dream-country-the-sandman-3/index.html", "title": "Dream Country (The Sandman, #3)", "date": 1333112685000, "score": 2.8988698959350585, "detailed_score": [1.0, 0.4, 0.9992465972900391]}, {"url": "/goodreads/brief-lives-the-sandman-7/index.html", "title": "Brief Lives (The Sandman, #7)", "date": 1394109903000, "score": 2.8979674220085143, "detailed_score": [1.0, 0.4, 0.9986449480056763]}, {"url": "/goodreads/the-kindly-ones-the-sandman-9/index.html", "title": "The Kindly Ones (The Sandman, #9)", "date": 1333112721000, "score": 2.880869859457016, "detailed_score": [1.0, 0.4, 0.987246572971344]}, {"url": "/goodreads/worlds-end-the-sandman-8/index.html", "title": "Worlds' End (The Sandman, #8)", "date": 1333112727000, "score": 2.8685742557048797, "detailed_score": [1.0, 0.4, 0.9790495038032532]}, {"url": "/goodreads/preludes-nocturnes-the-sandman-1/index.html", "title": "Preludes & Nocturnes (The Sandman, #1)", "date": 1333112678000, "score": 2.836660314689983, "detailed_score": [1.0, 0.36363636363636365, 0.9820159673690796]}, {"url": "/goodreads/fables-reflections-the-sandman-6/index.html", "title": "Fables & Reflections (The Sandman, #6)", "date": 1333112714000, "score": 2.832227964292873, "detailed_score": [1.0, 0.36363636363636365, 0.9790610671043396]}, {"url": "/goodreads/the-consuming-fire-the-interdependency-2/index.html", "title": "The Consuming Fire (The Interdependency, #2)", "date": 1570859978000, "score": 2.6774864315986635, "detailed_score": [1.0, 0.2, 0.9849909543991089]}]