[{"url": "/goodreads/mistakes-were-made-but-not-by-me/index.html", "title": "Mistakes Were Made (But Not By Me)", "date": 1532736000000, "score": 2.4999942779541016, "detailed_score": [1.0, 0.0, 0.9999961853027344]}, {"url": "/goodreads/being-mortal-medicine-and-what-matters-in-the-end/index.html", "title": "Being Mortal: Medicine and What Matters in the End", "date": 1443312000000, "score": 2.4999773800373077, "detailed_score": [1.0, 0.0, 0.9999849200248718]}, {"url": "/goodreads/forensics-the-anatomy-of-crime/index.html", "title": "Forensics: The Anatomy of Crime", "date": 1449014400000, "score": 2.4996569454669952, "detailed_score": [1.0, 0.0, 0.9997712969779968]}, {"url": "/goodreads/killers-of-the-flower-moon-oil-money-murder-and-the-birth-of-the-fbi/index.html", "title": "Killers of the Flower Moon: Oil, Money, Murder and the Birth of the FBI", "date": 1527120000000, "score": 2.4995983839035034, "detailed_score": [1.0, 0.0, 0.999732255935669]}, {"url": "/goodreads/the-man-who-mistook-his-wife-for-a-hat/index.html", "title": "The Man Who Mistook His Wife for a Hat", "date": 1493683200000, "score": 2.4995540380477905, "detailed_score": [1.0, 0.0, 0.9997026920318604]}, {"url": "/goodreads/selfish-whining-monkeys/index.html", "title": "Selfish Whining Monkeys", "date": 1436745600000, "score": 2.499291718006134, "detailed_score": [1.0, 0.0, 0.9995278120040894]}, {"url": "/goodreads/sapiens-a-brief-history-of-humankind/index.html", "title": "Sapiens: A Brief History of Humankind", "date": 1503187200000, "score": 2.4992441534996033, "detailed_score": [1.0, 0.0, 0.9994961023330688]}, {"url": "/goodreads/a-libertarian-walks-into-a-bear-the-utopian-plot-to-liberate-an-american-town-and-some-bears/index.html", "title": "A Libertarian Walks Into a Bear: The Utopian Plot to Liberate an American Town (And Some Bears)", "date": 1616630400000, "score": 2.4992334246635437, "detailed_score": [1.0, 0.0, 0.9994889497756958]}, {"url": "/goodreads/in-extremis-the-life-of-war-correspondent-marie-colvin/index.html", "title": "In Extremis: The Life of War Correspondent Marie Colvin", "date": 1600646400000, "score": 2.499144285917282, "detailed_score": [1.0, 0.0, 0.9994295239448547]}, {"url": "/goodreads/the-lonely-city-adventures-in-the-art-of-being-alone/index.html", "title": "The Lonely City: Adventures in the Art of Being Alone", "date": 1519454891000, "score": 2.4990687370300293, "detailed_score": [1.0, 0.0, 0.9993791580200195]}]