[{"url": "/2010/06/08/smarter-internet/index.html", "title": "Made smarter by the internet?", "date": 1275973222000, "score": 2.4996191263198853, "detailed_score": [1.0, 0.0, 0.9997460842132568]}, {"url": "/2010/11/08/internet-15-years-ago/index.html", "title": "The view of the internet, 15 years ago", "date": 1289224854000, "score": 2.3545899306024825, "detailed_score": [0.8571428571428571, 0.0, 0.9982980489730835]}, {"url": "/2011/01/05/wikileaks/index.html", "title": "Wikileaks as reality television", "date": 1294216230000, "score": 2.340980223246983, "detailed_score": [0.8571428571428571, 0.0, 0.989224910736084]}, {"url": "/2010/06/11/power-comics/index.html", "title": "The power of comics", "date": 1276272006000, "score": 2.3397675965513502, "detailed_score": [0.8571428571428571, 0.0, 0.9884164929389954]}, {"url": "/2010/06/29/getting-rid-of-the-laptop/index.html", "title": "Getting rid of the laptop", "date": 1277787602000, "score": 2.156136135260264, "detailed_score": [0.6666666666666666, 0.0, 0.9929796457290649]}, {"url": "/2013/11/14/numbers/index.html", "title": "Too many numbers", "date": 1384423205000, "score": 2.1379016737143197, "detailed_score": [0.6666666666666666, 0.0, 0.9808233380317688]}, {"url": "/2013/09/25/nonprophecy/index.html", "title": "A non-prophecy from ten years ago", "date": 1380120521000, "score": 2.0682063443320136, "detailed_score": [0.5714285714285714, 0.0, 0.9978518486022949]}, {"url": "/2011/05/17/work-life/index.html", "title": "Not a work/life balance", "date": 1305615658000, "score": 1.899970942735672, "detailed_score": [0.4, 0.0, 0.999980628490448]}, {"url": "/2011/07/05/arts-humanities/index.html", "title": "On not funding the arts and humanities", "date": 1309849213000, "score": 1.89965962767601, "detailed_score": [0.4, 0.0, 0.9997730851173401]}, {"url": "/2010/11/14/man-middle-earth/index.html", "title": "It's hard being a man in Middle Earth", "date": 1289770594000, "score": 1.8988082945346831, "detailed_score": [0.4, 0.0, 0.9992055296897888]}]