[{"url": "/2012/02/22/studentships/index.html", "title": "Studentships available", "date": 1329926215000, "score": 2.47463595867157, "detailed_score": [1.0, 0.0, 0.9830906391143799]}, {"url": "/2012/04/26/brazil-science/index.html", "title": "Brazilian \"Science without Borders\" studentships available", "date": 1335444378000, "score": 2.4434942603111267, "detailed_score": [1.0, 0.0, 0.9623295068740845]}, {"url": "/2012/05/17/5-studentships/index.html", "title": "5 studentships in Computer Science and St Andrews", "date": 1337251377000, "score": 2.426362097263336, "detailed_score": [1.0, 0.0, 0.9509080648422241]}, {"url": "/2015/03/10/studentships-st-andrews/index.html", "title": "PhD studentships in St Andrews", "date": 1425988040000, "score": 2.3881661229663425, "detailed_score": [0.6666666666666666, 0.2222222222222222, 0.9995181560516357]}, {"url": "/2013/12/09/funded-phd-positions/index.html", "title": "Funded PhD positions available", "date": 1386582361000, "score": 2.3414340847068362, "detailed_score": [0.6666666666666666, 0.2222222222222222, 0.9683634638786316]}, {"url": "/2015/03/05/phd-studentships-university-college-cork/index.html", "title": "PhD Studentships at University College Cork", "date": 1425552680000, "score": 2.2589003364245097, "detailed_score": [0.6666666666666666, 0.2, 0.928155779838562]}, {"url": "/2014/06/10/data-science-lancaster/index.html", "title": "Scholarships available to study data science in Lancaster", "date": 1402411427000, "score": 2.242127572045182, "detailed_score": [0.6666666666666666, 0.18181818181818182, 0.9290951490402222]}, {"url": "/2015/02/03/phd-cs-med/index.html", "title": "Fully-funded PhD scholarship available", "date": 1422965538000, "score": 2.191247714890374, "detailed_score": [0.5, 0.2222222222222222, 0.9793503284454346]}, {"url": "/2011/06/06/lectureship-computer-science-st-andrews/index.html", "title": "Lectureship in Computer Science at St Andrews", "date": 1307365930000, "score": 2.179820942878723, "detailed_score": [0.8, 0.0, 0.9198806285858154]}, {"url": "/2012/08/03/mscphd-wireless-location/index.html", "title": "MSc/PhD positions available in wireless location systems", "date": 1343991379000, "score": 2.1681129217147825, "detailed_score": [0.8, 0.0, 0.9120752811431885]}]