[{"url": "/goodreads/unix-a-history-and-a-memoir/index.html", "title": "UNIX: A History and a Memoir", "date": 1672617600000, "score": 2.771854328257697, "detailed_score": [1.0, 0.2857142857142857, 0.9907600283622742]}, {"url": "/goodreads/noise-a-human-history-of-sound-and-listening/index.html", "title": "Noise: a Human History of Sound and Listening", "date": 1665792000000, "score": 2.731859340932634, "detailed_score": [0.8, 0.4444444444444444, 0.9916099309921265]}, {"url": "/goodreads/the-first-world-war-a-complete-history/index.html", "title": "The First World War: A Complete History", "date": 1671667200000, "score": 2.7008752359284296, "detailed_score": [1.0, 0.2222222222222222, 0.9857686758041382]}, {"url": "/goodreads/atoms-and-ashes-a-global-history-of-nuclear-disasters/index.html", "title": "Atoms and Ashes: A Global History of Nuclear Disasters", "date": 1666310400000, "score": 2.680978399515152, "detailed_score": [1.0, 0.2, 0.9873189330101013]}, {"url": "/goodreads/empire-of-pain-the-secret-history-of-the-sackler-dynasty/index.html", "title": "Empire of Pain: The Secret History of the Sackler Dynasty", "date": 1662422400000, "score": 2.6744011759757997, "detailed_score": [1.0, 0.2, 0.9829341173171997]}, {"url": "/goodreads/day-of-the-assassins-a-history-of-political-murder/index.html", "title": "Day of the Assassins: A History of Political Murder", "date": 1685404800000, "score": 2.6725875867737665, "detailed_score": [1.0, 0.2222222222222222, 0.9669102430343628]}, {"url": "/goodreads/nuclear-folly-a-history-of-the-cuban-missile-crisis/index.html", "title": "Nuclear Folly: A History of the Cuban Missile Crisis", "date": 1631404800000, "score": 2.672161263227463, "detailed_score": [1.0, 0.2, 0.9814408421516418]}, {"url": "/goodreads/around-the-world-in-eighty-games-from-tarot-to-tic-tac-toe-catan-to-chutes-and-ladders-a-mathematician-unlocks-the-secrets-of-the-worlds-greatest-games/index.html", "title": "Around the World in Eighty Games: From Tarot to Tic-Tac-Toe, Catan to Chutes and Ladders, a Mathematician Unlocks the Secrets of the World's Greatest Games", "date": 1703376000000, "score": 2.5831346653009715, "detailed_score": [1.0, 0.10526315789473684, 0.9852476716041565]}, {"url": "/goodreads/estates-an-intimate-history/index.html", "title": "Estates: An Intimate History", "date": 1702944000000, "score": 2.5463854125567846, "detailed_score": [0.8, 0.2857142857142857, 0.9737807512283325]}, {"url": "/goodreads/the-secret-history-of-wonder-woman/index.html", "title": "The Secret History of Wonder Woman", "date": 1658534400000, "score": 2.5136807441711424, "detailed_score": [0.8, 0.25, 0.9757871627807617]}]