[{"url": "/goodreads/spike-the-virus-vs-the-people-the-inside-story/index.html", "title": "Spike: The Virus vs. The People - the Inside Story", "date": 1665905360000, "score": 2.5963974595069885, "detailed_score": [1.0, 0.125, 0.9809316396713257]}, {"url": "/goodreads/dopesick-dealers-doctors-and-the-drug-company-that-addicted-america/index.html", "title": "Dopesick: Dealers, Doctors, and the Drug Company that Addicted America", "date": 1640217600000, "score": 2.4999998211860657, "detailed_score": [1.0, 0.0, 0.9999998807907104]}, {"url": "/goodreads/infinite-detail/index.html", "title": "Infinite Detail", "date": 1610179341000, "score": 2.4999724626541138, "detailed_score": [1.0, 0.0, 0.9999816417694092]}, {"url": "/goodreads/seven-games-a-human-history/index.html", "title": "Seven Games: A Human History", "date": 1665808973000, "score": 2.4999658465385437, "detailed_score": [1.0, 0.0, 0.9999772310256958]}, {"url": "/goodreads/travellers-in-the-third-reich/index.html", "title": "Travellers in the Third Reich", "date": 1635206400000, "score": 2.499938577413559, "detailed_score": [1.0, 0.0, 0.9999590516090393]}, {"url": "/goodreads/the-rise-and-fall-of-dodo-dodo-1/index.html", "title": "The Rise and Fall of D.O.D.O. (D.O.D.O. #1)", "date": 1609200000000, "score": 2.499913364648819, "detailed_score": [1.0, 0.0, 0.9999422430992126]}, {"url": "/goodreads/the-windup-girl/index.html", "title": "The Windup Girl", "date": 1598486400000, "score": 2.4998971819877625, "detailed_score": [1.0, 0.0, 0.9999314546585083]}, {"url": "/goodreads/tickbox/index.html", "title": "Tickbox", "date": 1599782400000, "score": 2.4998808205127716, "detailed_score": [1.0, 0.0, 0.9999205470085144]}, {"url": "/goodreads/accidental-gods-on-men-unwittingly-turned-divine/index.html", "title": "Accidental Gods: On Men Unwittingly Turned Divine", "date": 1665811839000, "score": 2.4998713433742523, "detailed_score": [1.0, 0.0, 0.9999142289161682]}, {"url": "/goodreads/sea-room-an-island-life-in-the-hebrides/index.html", "title": "Sea Room: An Island Life in the Hebrides", "date": 1625788800000, "score": 2.49984148144722, "detailed_score": [1.0, 0.0, 0.9998943209648132]}]