[{"url": "/goodreads/good-strategybad-strategy-the-difference-and-why-it-matters/index.html", "title": "Good Strategy/Bad Strategy: The difference and why it matters", "date": 1570859855000, "score": 2.5, "detailed_score": [1.0, 0.0, 1.0]}, {"url": "/goodreads/savage-arena/index.html", "title": "Savage Arena", "date": 1623110400000, "score": 2.499998301267624, "detailed_score": [1.0, 0.0, 0.9999988675117493]}, {"url": "/goodreads/their-darkest-hour/index.html", "title": "Their Darkest Hour", "date": 1369440000000, "score": 2.4999948143959045, "detailed_score": [1.0, 0.0, 0.999996542930603]}, {"url": "/goodreads/jack-of-shadows/index.html", "title": "Jack of Shadows", "date": 1577003221000, "score": 2.4999902546405792, "detailed_score": [1.0, 0.0, 0.9999935030937195]}, {"url": "/goodreads/circe/index.html", "title": "Circe", "date": 1548575306000, "score": 2.49998739361763, "detailed_score": [1.0, 0.0, 0.9999915957450867]}, {"url": "/goodreads/compelling-people-the-hidden-qualities-that-make-us-influential/index.html", "title": "Compelling People: The Hidden Qualities That Make Us Influential", "date": 1418784253000, "score": 2.4999871253967285, "detailed_score": [1.0, 0.0, 0.9999914169311523]}, {"url": "/goodreads/on-lies-secrets-and-silence-selected-prose-1966-1978/index.html", "title": "On Lies, Secrets, and Silence. Selected Prose 1966-1978", "date": 1424513158000, "score": 2.4999815821647644, "detailed_score": [1.0, 0.0, 0.9999877214431763]}, {"url": "/goodreads/the-missing-cryptoqueen-the-billion-dollar-cryptocurrency-con-and-the-woman-who-got-away-with-it/index.html", "title": "The Missing Cryptoqueen: The Billion Dollar Cryptocurrency Con and the Woman Who Got Away with It", "date": 1665807982000, "score": 2.4999779164791107, "detailed_score": [1.0, 0.0, 0.9999852776527405]}, {"url": "/goodreads/we-dont-know-ourselves/index.html", "title": "We Don't Know Ourselves", "date": 1636502400000, "score": 2.4999669194221497, "detailed_score": [1.0, 0.0, 0.9999779462814331]}, {"url": "/goodreads/the-atrocity-archives-laundry-files-1/index.html", "title": "The Atrocity Archives (Laundry Files, #1)", "date": 1581465600000, "score": 2.4999510049819946, "detailed_score": [1.0, 0.0, 0.9999673366546631]}]