[{"url": "/goodreads/a-book-of-silence/index.html", "title": "A Book of Silence", "date": 1644624000000, "score": 2.7183112932576075, "detailed_score": [1.0, 0.2222222222222222, 0.9973927140235901]}, {"url": "/goodreads/the-book-of-legendary-lands/index.html", "title": "The Book of Legendary Lands", "date": 1618808098000, "score": 2.69421501159668, "detailed_score": [1.0, 0.2, 0.9961433410644531]}, {"url": "/goodreads/the-eye-of-the-world-the-wheel-of-time-1/index.html", "title": "The Eye of the World (The Wheel of Time, #1)", "date": 1646352000000, "score": 2.64015338741816, "detailed_score": [1.0, 0.15384615384615385, 0.9908714890480042]}, {"url": "/goodreads/spike-the-virus-vs-the-people-the-inside-story/index.html", "title": "Spike: The Virus vs. The People - the Inside Story", "date": 1665905360000, "score": 2.4990682899951935, "detailed_score": [1.0, 0.0, 0.9993788599967957]}, {"url": "/goodreads/i-am-an-island/index.html", "title": "I Am an Island", "date": 1665904576000, "score": 2.4990546107292175, "detailed_score": [1.0, 0.0, 0.999369740486145]}, {"url": "/goodreads/furious-hours-murder-fraud-and-the-last-trial-of-harper-lee/index.html", "title": "Furious Hours: Murder, Fraud, and the Last Trial of Harper Lee", "date": 1651372318000, "score": 2.4988193809986115, "detailed_score": [1.0, 0.0, 0.999212920665741]}, {"url": "/goodreads/the-living-mountain/index.html", "title": "The Living Mountain", "date": 1622867208000, "score": 2.4980251789093018, "detailed_score": [1.0, 0.0, 0.9986834526062012]}, {"url": "/goodreads/ten-days-that-shook-the-world/index.html", "title": "Ten Days that Shook the World", "date": 1640995200000, "score": 2.4968808591365814, "detailed_score": [1.0, 0.0, 0.997920572757721]}, {"url": "/goodreads/time-on-rock-a-climbers-route-into-the-mountains/index.html", "title": "Time on Rock: A Climber's Route into the Mountains", "date": 1665899432000, "score": 2.4968782663345337, "detailed_score": [1.0, 0.0, 0.9979188442230225]}, {"url": "/goodreads/culture-warlords-my-journey-into-the-dark-web-of-white-supremacy/index.html", "title": "Culture Warlords: My Journey Into the Dark Web of White Supremacy", "date": 1631318400000, "score": 2.496456265449524, "detailed_score": [1.0, 0.0, 0.9976375102996826]}]