[{"url": "/goodreads/playing-to-win-how-strategy-really-works/index.html", "title": "Playing to Win: How Strategy Really Works", "date": 1366416000000, "score": 2.802875419457753, "detailed_score": [1.0, 0.3333333333333333, 0.9796947240829468]}, {"url": "/goodreads/maos-great-famine-the-history-of-chinas-most-devastating-catastrophe-1958-62/index.html", "title": "Mao's Great Famine: The History Of China's Most Devastating Catastrophe, 1958-62", "date": 1391920694000, "score": 2.4999996423721313, "detailed_score": [1.0, 0.0, 0.9999997615814209]}, {"url": "/goodreads/a-canticle-for-leibowitz-st-leibowitz-1/index.html", "title": "A Canticle for Leibowitz (St. Leibowitz, #1)", "date": 1438646400000, "score": 2.4999932944774628, "detailed_score": [1.0, 0.0, 0.9999955296516418]}, {"url": "/goodreads/the-dreyfus-affair-the-story-of-the-most-infamous-miscarriage-of-justice-in-french-history/index.html", "title": "The Dreyfus Affair: The Story of the Most Infamous Miscarriage of Justice in French History", "date": 1430317734000, "score": 2.4999914169311523, "detailed_score": [1.0, 0.0, 0.9999942779541016]}, {"url": "/goodreads/aurora/index.html", "title": "Aurora", "date": 1595980800000, "score": 2.499959319829941, "detailed_score": [1.0, 0.0, 0.9999728798866272]}, {"url": "/goodreads/the-reality-dysfunction-nights-dawn-1/index.html", "title": "The Reality Dysfunction (Night's Dawn, #1)", "date": 1532840131000, "score": 2.4999503791332245, "detailed_score": [1.0, 0.0, 0.9999669194221497]}, {"url": "/goodreads/orientalism/index.html", "title": "Orientalism", "date": 1542436760000, "score": 2.4999389350414276, "detailed_score": [1.0, 0.0, 0.9999592900276184]}, {"url": "/goodreads/the-black-death-in-london/index.html", "title": "The Black Death in London", "date": 1419398667000, "score": 2.4999289214611053, "detailed_score": [1.0, 0.0, 0.9999526143074036]}, {"url": "/goodreads/seven-brief-lessons-on-physics/index.html", "title": "Seven Brief Lessons on Physics", "date": 1542437268000, "score": 2.49990513920784, "detailed_score": [1.0, 0.0, 0.9999367594718933]}, {"url": "/goodreads/lords-of-finance-1929-the-great-depression-and-the-bankers-who-broke-the-world/index.html", "title": "Lords of Finance: 1929, The Great Depression, and the Bankers Who Broke the World", "date": 1407542400000, "score": 2.4999037981033325, "detailed_score": [1.0, 0.0, 0.9999358654022217]}]