[{"url": "/2020/08/06/how-to-write-an-abstract/index.html", "title": "How to write an abstract", "date": 1596713121000, "score": 2.832926531632741, "detailed_score": [0.3333333333333333, 1.0, 0.999728798866272]}, {"url": "/2010/12/16/inauguration/index.html", "title": "Inauguration", "date": 1292486404000, "score": 2.2563488364219664, "detailed_score": [0.8, 0.0, 0.970899224281311]}, {"url": "/2011/07/01/metrics/index.html", "title": "Metrics and the Research Evaluation Framework", "date": 1309503629000, "score": 2.2485076665878294, "detailed_score": [0.8, 0.0, 0.9656717777252197]}, {"url": "/2011/07/05/arts-humanities/index.html", "title": "On not funding the arts and humanities", "date": 1309849213000, "score": 2.1859250247478483, "detailed_score": [0.8, 0.0, 0.9239500164985657]}, {"url": "/2010/05/08/grey-philistines/index.html", "title": "Are the grey philistines really in charge?", "date": 1273339739000, "score": 2.165448764959971, "detailed_score": [0.6666666666666666, 0.0, 0.9991880655288696]}, {"url": "/2011/05/04/balance-of-power/index.html", "title": "The shifting balance of university power", "date": 1304503217000, "score": 2.1589763263861337, "detailed_score": [0.6666666666666666, 0.0, 0.9948731064796448]}, {"url": "/2010/10/22/first-year/index.html", "title": "The first year", "date": 1287735317000, "score": 2.1546714703241983, "detailed_score": [0.6666666666666666, 0.0, 0.9920032024383545]}, {"url": "/2011/11/25/inaugural/index.html", "title": "Inaugural lecture", "date": 1322225350000, "score": 2.1530752877394357, "detailed_score": [0.6666666666666666, 0.0, 0.9909390807151794]}, {"url": "/2010/10/25/cs-university-principals/index.html", "title": "Computer scientists as university principals", "date": 1287990046000, "score": 2.1527671019236245, "detailed_score": [0.6666666666666666, 0.0, 0.9907336235046387]}, {"url": "/2011/02/25/hiring-2/index.html", "title": "Hiring academics", "date": 1298620835000, "score": 2.095445970694224, "detailed_score": [0.6666666666666666, 0.0, 0.9525195360183716]}]