[{"url": "/2014/01/07/sleepysketch-release/index.html", "title": "First SleepySketch release", "date": 1389098174000, "score": 2.4973781446615853, "detailed_score": [0.6666666666666666, 0.4, 0.9538076519966125]}, {"url": "/2013/07/25/sleepy-sketches/index.html", "title": "Sleepy sketches", "date": 1374753601000, "score": 2.4681612849235535, "detailed_score": [1.0, 0.0, 0.9787741899490356]}, {"url": "/2013/08/27/arduino-breadboard/index.html", "title": "Low-power Arduino-on-a-breadboard", "date": 1377600465000, "score": 2.041949524120851, "detailed_score": [0.5454545454545454, 0.0, 0.9976633191108704]}, {"url": "/2013/07/03/xbee-arduino/index.html", "title": "The xbee-arduino library", "date": 1372836622000, "score": 1.9996569454669952, "detailed_score": [0.5, 0.0, 0.9997712969779968]}, {"url": "/2013/07/31/power/index.html", "title": "Basic power measurements", "date": 1375290775000, "score": 1.9929578602313995, "detailed_score": [0.5, 0.0, 0.9953052401542664]}, {"url": "/2013/06/01/actor-systems/index.html", "title": "Actor systems", "date": 1370111368000, "score": 1.9849101142449812, "detailed_score": [0.5454545454545454, 0.0, 0.9596370458602905]}, {"url": "/2013/07/23/arduino-watchdog/index.html", "title": "Understanding Arduino sleep modes: the watchdog timer", "date": 1374589287000, "score": 1.9661067128181458, "detailed_score": [0.5, 0.0, 0.9774044752120972]}, {"url": "/2013/08/02/xbee-sleeping/index.html", "title": "XBee sleeping", "date": 1375454490000, "score": 1.9606333054029026, "detailed_score": [0.46153846153846156, 0.0, 0.999396562576294]}, {"url": "/2013/06/28/soldering/index.html", "title": "First bit of soldering done", "date": 1372437897000, "score": 1.8977053701877593, "detailed_score": [0.4, 0.0, 0.9984702467918396]}, {"url": "/2013/08/28/uploading-sketches/index.html", "title": "Uploading sketches to a breadboard Arduino", "date": 1377723004000, "score": 1.8627797554839742, "detailed_score": [0.36363636363636365, 0.0, 0.999428927898407]}]