[{"url": "/2014/03/12/data-scientists/index.html", "title": "No data scientists", "date": 1394622029000, "score": 2.2320402403672537, "detailed_score": [0.3333333333333333, 0.4, 0.9991379380226135]}, {"url": "/2013/07/31/big-rich/index.html", "title": "Big, or just rich?", "date": 1375279129000, "score": 2.074479987223943, "detailed_score": [0.25, 0.3333333333333333, 0.9940977692604065]}, {"url": "/2010/06/29/getting-rid-of-the-laptop/index.html", "title": "Getting rid of the laptop", "date": 1277787602000, "score": 2.042778466429029, "detailed_score": [0.5714285714285714, 0.0, 0.9808999300003052]}, {"url": "/2014/04/05/big-data/index.html", "title": "Let's teach everyone about big data", "date": 1396699788000, "score": 2.0377944750445227, "detailed_score": [0.2857142857142857, 0.2857142857142857, 0.977577269077301]}, {"url": "/2011/10/21/tablet-convert/index.html", "title": "A convert to tablet computing", "date": 1319232433000, "score": 2.0338861388819556, "detailed_score": [0.5714285714285714, 0.0, 0.9749717116355896]}, {"url": "/2012/09/27/awareness/index.html", "title": "What's new for awareness researchers?: an interview", "date": 1348729241000, "score": 2.032297203938166, "detailed_score": [0.6666666666666666, 0.0, 0.9104203581809998]}, {"url": "/2011/09/09/smart-grids/index.html", "title": "An issue for smart grids", "date": 1315549809000, "score": 1.999876707792282, "detailed_score": [0.5, 0.0, 0.9999178051948547]}, {"url": "/2011/03/23/situations/index.html", "title": "The next challenges for situation recognition", "date": 1300873518000, "score": 1.998159110546112, "detailed_score": [0.5, 0.0, 0.9987727403640747]}, {"url": "/2011/06/03/pervasive-healthcare/index.html", "title": "Pervasive healthcare", "date": 1307106035000, "score": 1.9971842169761658, "detailed_score": [0.5, 0.0, 0.9981228113174438]}, {"url": "/2013/03/07/studentship/index.html", "title": "Studentship available in Newcastle upon Tyne", "date": 1362674963000, "score": 1.9353648466723306, "detailed_score": [0.5714285714285714, 0.0, 0.9092908501625061]}]