[{"url": "/2012/10/05/typewheel/index.html", "title": "The type wheel turns again", "date": 1349420423000, "score": 1.961341368300574, "detailed_score": [0.25, 0.2857142857142857, 0.9504180550575256]}, {"url": "/2021/12/06/talk-at-uk-systems-on-unit-testing-stochastic-code/index.html", "title": "Talk at UK Systems on unit testing stochastic code", "date": 1638809370000, "score": 1.9040796127584245, "detailed_score": [0.4444444444444444, 0.0, 0.9730901122093201]}, {"url": "/2021/09/06/new-version-of-epyc-released/index.html", "title": "New version of epyc released", "date": 1630936248000, "score": 1.8852374792098998, "detailed_score": [0.4, 0.0, 0.9901583194732666]}, {"url": "/2021/05/14/new-faster-release-of-epydemic/index.html", "title": "New, faster, release of epydemic", "date": 1620984797000, "score": 1.8601935695518148, "detailed_score": [0.36363636363636365, 0.0, 0.997704803943634]}, {"url": "/2021/06/10/generating-functions-for-epydemic/index.html", "title": "Generating functions for epydemic", "date": 1623349336000, "score": 1.8327782948811848, "detailed_score": [0.3333333333333333, 0.0, 0.9996299743652344]}, {"url": "/2011/01/10/unpopular-book/index.html", "title": "How to publish an unpopular book?", "date": 1294646404000, "score": 1.7851387730666568, "detailed_score": [0.2857142857142857, 0.0, 0.9996163249015808]}, {"url": "/2012/05/04/postmodernism-programming/index.html", "title": "The post-modernisation of programming languages", "date": 1336133833000, "score": 1.7790199390479495, "detailed_score": [0.2857142857142857, 0.0, 0.9955371022224426]}, {"url": "/2012/08/08/forth-32-years/index.html", "title": "Forth, 2^5 years ago", "date": 1344443991000, "score": 1.7708099654742648, "detailed_score": [0.2857142857142857, 0.0, 0.9900637865066528]}, {"url": "/2011/06/27/computing-experience/index.html", "title": "The changing student computing experience", "date": 1309186855000, "score": 1.7591278723308017, "detailed_score": [0.2857142857142857, 0.0, 0.9822757244110107]}, {"url": "/2011/05/23/code/index.html", "title": "Why we have code", "date": 1306134059000, "score": 1.7512312701770236, "detailed_score": [0.2857142857142857, 0.0, 0.9770113229751587]}]