[{"url": "/2012/02/22/studentships/index.html", "title": "Studentships available", "date": 1329926215000, "score": 2.9922890961170197, "detailed_score": [1.0, 0.5, 0.9948593974113464]}, {"url": "/2012/05/17/5-studentships/index.html", "title": "5 studentships in Computer Science and St Andrews", "date": 1337251377000, "score": 2.665810326735179, "detailed_score": [1.0, 0.16666666666666666, 0.9994291067123413]}, {"url": "/2012/08/03/mscphd-wireless-location/index.html", "title": "MSc/PhD positions available in wireless location systems", "date": 1343991379000, "score": 2.452434508005778, "detailed_score": [0.8, 0.16666666666666666, 0.9905118942260742]}, {"url": "/2012/12/20/600th-scholarships/index.html", "title": "Six 600th anniversary PhD scholarships", "date": 1356031342000, "score": 2.436940997838974, "detailed_score": [1.0, 0.0, 0.9579606652259827]}, {"url": "/2013/12/09/funded-phd-positions/index.html", "title": "Funded PhD positions available", "date": 1386582361000, "score": 2.3658381323019664, "detailed_score": [0.6666666666666666, 0.2, 0.9994476437568665]}, {"url": "/2015/09/18/phd-data-science/index.html", "title": "PhD data science studentships available at Trinity College Dublin", "date": 1442573657000, "score": 2.352667680808476, "detailed_score": [0.5714285714285714, 0.2857142857142857, 0.9970165491104126]}, {"url": "/2015/03/05/phd-studentships-university-college-cork/index.html", "title": "PhD Studentships at University College Cork", "date": 1425552680000, "score": 2.341357146248673, "detailed_score": [0.6666666666666666, 0.18181818181818182, 0.9952481985092163]}, {"url": "/2014/06/10/data-science-lancaster/index.html", "title": "Scholarships available to study data science in Lancaster", "date": 1402411427000, "score": 2.3268650074799853, "detailed_score": [0.6666666666666666, 0.16666666666666666, 0.9956877827644348]}, {"url": "/2015/03/10/studentships-st-andrews/index.html", "title": "PhD studentships in St Andrews", "date": 1425988040000, "score": 2.3187352339426677, "detailed_score": [0.6666666666666666, 0.2, 0.968045711517334]}, {"url": "/2011/06/06/lectureship-computer-science-st-andrews/index.html", "title": "Lectureship in Computer Science at St Andrews", "date": 1307365930000, "score": 2.289631116390228, "detailed_score": [0.8, 0.0, 0.9930874109268188]}]