[{"url": "/2011/03/23/situations/index.html", "title": "The next challenges for situation recognition", "date": 1300873518000, "score": 2.0436691777272658, "detailed_score": [0.5454545454545454, 0.0, 0.9988097548484802]}, {"url": "/2010/06/18/contextual-processes/index.html", "title": "Contextual processes", "date": 1276837253000, "score": 1.9969067871570587, "detailed_score": [0.5, 0.0, 0.9979378581047058]}, {"url": "/2011/05/23/code/index.html", "title": "Why we have code", "date": 1306134059000, "score": 1.898956799507141, "detailed_score": [0.4, 0.0, 0.9993045330047607]}, {"url": "/2011/06/27/computing-experience/index.html", "title": "The changing student computing experience", "date": 1309186855000, "score": 1.896965616941452, "detailed_score": [0.4, 0.0, 0.997977077960968]}, {"url": "/2012/08/08/forth-32-years/index.html", "title": "Forth, 2^5 years ago", "date": 1344443991000, "score": 1.8908747673034667, "detailed_score": [0.4, 0.0, 0.9939165115356445]}, {"url": "/2012/05/04/postmodernism-programming/index.html", "title": "The post-modernisation of programming languages", "date": 1336133833000, "score": 1.8811564981937408, "detailed_score": [0.4, 0.0, 0.9874376654624939]}, {"url": "/2011/01/10/unpopular-book/index.html", "title": "How to publish an unpopular book?", "date": 1294646404000, "score": 1.8623837172985076, "detailed_score": [0.4, 0.0, 0.9749224781990051]}, {"url": "/2012/10/05/typewheel/index.html", "title": "The type wheel turns again", "date": 1349420423000, "score": 1.8605420779098165, "detailed_score": [0.36363636363636365, 0.0, 0.9979371428489685]}, {"url": "/2010/03/12/forth-for-sensors/index.html", "title": "Forth for sensors?", "date": 1268373610000, "score": 1.8350888084281576, "detailed_score": [0.36363636363636365, 0.0, 0.9809682965278625]}, {"url": "/2011/05/27/smalltalk/index.html", "title": "Mainstreaming Smalltalk", "date": 1306479629000, "score": 1.8347032855857504, "detailed_score": [0.36363636363636365, 0.0, 0.9807112812995911]}]